Workbook

Sheet Instrucoes
B2: JM NFE — Planilha de LIQUIDAÇÃO com atualização por competência
B4: FLUXO DE USO:
B5: 1. Aba 'Indices': preencha a tabela com o FATOR de cada competência, extraído da
B6: tabela oficial do TRT/CSJT do período dos autos (ou IPCA-E/SELIC por fase).
B7: Use o fator CONSOLIDADO (correção + juros) da tabela única, quando adotá-la.
B8: 2. Aba 'Verbas': lance cada parcela com sua COMPETÊNCIA e o VALOR HISTÓRICO.
B9: O fator é buscado automaticamente (PROCV) pela competência; o corrigido se calcula.
B10: 3. Aba 'Resumo': confira totais, FGTS, multa e descontos (apure isenções).
B11: 4. Aba 'Memoria': registre premissas, fontes e datas de extração dos índices.
B13: REGRA-MÃE: o índice segue o PERÍODO e a DECISÃO LIQUIDANDA. Veja o documento
B14: '06-tabelas-indices-2026-e-metodologia.md'. IPCA-E/SELIC são pós-fixados.
B16: AVISOS: instrumento de apoio (não substitui o julgamento do perito); verbas
... B23: Resultado (fórmula protegida)

Sheet Indices
B2: TABELA DE ÍNDICES POR COMPETÊNCIA (preencher da fonte oficial)
B3: Fator CONSOLIDADO (correção + juros) acumulado da competência até a data-base. Ex.: 1,0500 = +5%.
B4: Competência | C4: Fase | D4: Fator | E4: Fonte / data de extração
B5: 43831 | C5: pré-judicial | D5: 1 | E5: ____ (TRT/CSJT/IBGE/BACEN — data: __/__/__)
B6: 43862 | C6: pré-judicial | D6: 1 | E6: ____ (TRT/CSJT/IBGE/BACEN — data: __/__/__)
B7: 43891 | C7: pré-judicial | D7: 1 | E7: ____ (TRT/CSJT/IBGE/BACEN — data: __/__/__)
B8: 43922 | C8: pré-judicial | D8: 1 | E8: ____ (TRT/CSJT/IBGE/BACEN — data: __/__/__)
B9: 43952 | C9: pré-judicial | D9: 1 | E9: ____ (TRT/CSJT/IBGE/BACEN — data: __/__/__)
B10: 43983 | C10: pré-judicial | D10: 1 | E10: ____ (TRT/CSJT/IBGE/BACEN — data: __/__/__)
B11: 44013 | C11: pré-judicial | D11: 1 | E11: ____ (TRT/CSJT/IBGE/BACEN — data: __/__/__)
B12: 44044 | C12: pré-judicial | D12: 1 | E12: ____ (TRT/CSJT/IBGE/BACEN — data: __/__/__)
B13: 44075 | C13: pré-judicial | D13: 1 | E13: ____ (TRT/CSJT/IBGE/BACEN — data: __/__/__)
B14: 44105 | C14: pré-judicial | D14: 1 | E14: ____ (TRT/CSJT/IBGE/BACEN — data: __/__/__)
B15: 44136 | C15: pré-judicial | D15: 1 | E15: ____ (TRT/CSJT/IBGE/BACEN — data: __/__/__)
B16: 44166 | C16: pré-judicial | D16: 1 | E16: ____ (TRT/CSJT/IBGE/BACEN — data: __/__/__)
... B52: 45261 | C52: pré-judicial | D52: 1 | E52: ____ (TRT/CSJT/IBGE/BACEN — data: __/__/__)

Sheet Verbas
B2: PARCELAS — VALOR HISTÓRICO → CORRIGIDO POR COMPETÊNCIA
B4: Parcela | C4: Competência | D4: Valor histórico | E4: Fator | F4: Valor corrigido
B5: Saldo de salário | E5: =IF(C5="","",IFERROR(VLOOKUP(C5,Indices!$B$5:$D$52,3,FALSE),"VERIFICAR")) | F5: =IF(OR(D5="",E5="",E5="VERIFICAR"),0,ROUND(D5*E5,2))
B6: 13º proporcional | E6: =IF(C6="","",IFERROR(VLOOKUP(C6,Indices!$B$5:$D$52,3,FALSE),"VERIFICAR")) | F6: =IF(OR(D6="",E6="",E6="VERIFICAR"),0,ROUND(D6*E6,2))
B7: Férias prop. + 1/3 | E7: =IF(C7="","",IFERROR(VLOOKUP(C7,Indices!$B$5:$D$52,3,FALSE),"VERIFICAR")) | F7: =IF(OR(D7="",E7="",E7="VERIFICAR"),0,ROUND(D7*E7,2))
B8: Aviso prévio indenizado | E8: =IF(C8="","",IFERROR(VLOOKUP(C8,Indices!$B$5:$D$52,3,FALSE),"VERIFICAR")) | F8: =IF(OR(D8="",E8="",E8="VERIFICAR"),0,ROUND(D8*E8,2))
B9: Horas extras + reflexos | E9: =IF(C9="","",IFERROR(VLOOKUP(C9,Indices!$B$5:$D$52,3,FALSE),"VERIFICAR")) | F9: =IF(OR(D9="",E9="",E9="VERIFICAR"),0,ROUND(D9*E9,2))
B10: Diferenças salariais | E10: =IF(C10="","",IFERROR(VLOOKUP(C10,Indices!$B$5:$D$52,3,FALSE),"VERIFICAR")) | F10: =IF(OR(D10="",E10="",E10="VERIFICAR"),0,ROUND(D10*E10,2))
B11: (adicione linhas...) | E11: =IF(C11="","",IFERROR(VLOOKUP(C11,Indices!$B$5:$D$52,3,FALSE),"VERIFICAR")) | F11: =IF(OR(D11="",E11="",E11="VERIFICAR"),0,ROUND(D11*E11,2))
E12: =IF(C12="","",IFERROR(VLOOKUP(C12,Indices!$B$5:$D$52,3,FALSE),"VERIFICAR")) | F12: =IF(OR(D12="",E12="",E12="VERIFICAR"),0,ROUND(D12*E12,2))
E13: =IF(C13="","",IFERROR(VLOOKUP(C13,Indices!$B$5:$D$52,3,FALSE),"VERIFICAR")) | F13: =IF(OR(D13="",E13="",E13="VERIFICAR"),0,ROUND(D13*E13,2))
E14: =IF(C14="","",IFERROR(VLOOKUP(C14,Indices!$B$5:$D$52,3,FALSE),"VERIFICAR")) | F14: =IF(OR(D14="",E14="",E14="VERIFICAR"),0,ROUND(D14*E14,2))
E15: =IF(C15="","",IFERROR(VLOOKUP(C15,Indices!$B$5:$D$52,3,FALSE),"VERIFICAR")) | F15: =IF(OR(D15="",E15="",E15="VERIFICAR"),0,ROUND(D15*E15,2))
E16: =IF(C16="","",IFERROR(VLOOKUP(C16,Indices!$B$5:$D$52,3,FALSE),"VERIFICAR")) | F16: =IF(OR(D16="",E16="",E16="VERIFICAR"),0,ROUND(D16*E16,2))
E17: =IF(C17="","",IFERROR(VLOOKUP(C17,Indices!$B$5:$D$52,3,FALSE),"VERIFICAR")) | F17: =IF(OR(D17="",E17="",E17="VERIFICAR"),0,ROUND(D17*E17,2))
E18: =IF(C18="","",IFERROR(VLOOKUP(C18,Indices!$B$5:$D$52,3,FALSE),"VERIFICAR")) | F18: =IF(OR(D18="",E18="",E18="VERIFICAR"),0,ROUND(D18*E18,2))
E19: =IF(C19="","",IFERROR(VLOOKUP(C19,Indices!$B$5:$D$52,3,FALSE),"VERIFICAR")) | F19: =IF(OR(D19="",E19="",E19="VERIFICAR"),0,ROUND(D19*E19,2))
E20: =IF(C20="","",IFERROR(VLOOKUP(C20,Indices!$B$5:$D$52,3,FALSE),"VERIFICAR")) | F20: =IF(OR(D20="",E20="",E20="VERIFICAR"),0,ROUND(D20*E20,2))
E21: =IF(C21="","",IFERROR(VLOOKUP(C21,Indices!$B$5:$D$52,3,FALSE),"VERIFICAR")) | F21: =IF(OR(D21="",E21="",E21="VERIFICAR"),0,ROUND(D21*E21,2))
E22: =IF(C22="","",IFERROR(VLOOKUP(C22,Indices!$B$5:$D$52,3,FALSE),"VERIFICAR")) | F22: =IF(OR(D22="",E22="",E22="VERIFICAR"),0,ROUND(D22*E22,2))
E23: =IF(C23="","",IFERROR(VLOOKUP(C23,Indices!$B$5:$D$52,3,FALSE),"VERIFICAR")) | F23: =IF(OR(D23="",E23="",E23="VERIFICAR"),0,ROUND(D23*E23,2))
... E29: =IF(C29="","",IFERROR(VLOOKUP(C29,Indices!$B$5:$D$52,3,FALSE),"VERIFICAR")) | F29: =IF(OR(D29="",E29="",E29="VERIFICAR"),0,ROUND(D29*E29,2))
B30: TOTAL HISTÓRICO / CORRIGIDO | D30: =ROUND(SUM(D5:D29),2) | F30: =ROUND(SUM(F5:F29),2)
B31: Células 'VERIFICAR' = competência sem índice na aba 'Indices': preencha a tabela.

Sheet Resumo
B2: RESUMO DA LIQUIDAÇÃO
B4: Total das verbas (corrigido) | C4: =Verbas!F30 | D4: vem da aba 'Verbas' (já por competência)
B5: FGTS sobre verbas (8%) | C5: =ROUND(C4*0.08,2) | D5: conferir incidência verba a verba
B6: Saldo FGTS depositado (extrato) | C6: 0 | D6: base da multa — do extrato
B7: Multa de 40% do FGTS | C7: =ROUND(C6*0.4,2) | D7: se dispensa sem justa causa
B8: (-) INSS (apurado) | C8: 0 | D8: tabela vigente; verba a verba (isenções)
B9: (-) IRRF (apurado) | C9: 0 | D9: tabela RFB 2026; 13º exclusivo; isenções
B11: TOTAL GERAL LÍQUIDO | C11: =ROUND(C4+C5+C7-C8-C9,2) | D11: verbas corrigidas + FGTS + multa − INSS − IRRF
B13: CONTROLE DE QUALIDADE
B14: [ ] Índices buscados por competência na fonte oficial (data de extração anotada).
B15: [ ] Critério conforme a decisão liquidanda e a fase (pré-judicial/ajuizamento).
B16: [ ] Sem cumular SELIC com outro índice/juros no período aplicável.
B17: [ ] Isenções de INSS/IR observadas verba a verba; 13º em separado.
B18: [ ] Reconferência por método independente.
B19: [ ] Premissas e fontes na aba 'Memoria'.

Sheet Memoria
B2: MEMÓRIA / PREMISSAS E FONTES
B4: Premissa | C4: Critério adotado | D4: Fonte / fls. / data
B5: Decisão liquidanda (parâmetros) | C5: ____________________ | D5: ____________________
B6: Período/competências das parcelas | C6: ____________________ | D6: ____________________
B7: Data-base do cálculo | C7: ____________________ | D7: ____________________
B8: Critério de correção (fase) | C8: ____________________ | D8: ____________________
B9: Critério de juros | C9: ____________________ | D9: ____________________
B10: Tabela de índices (origem) | C10: ____________________ | D10: ____________________
B11: Data de extração dos índices | C11: ____________________ | D11: ____________________
B12: INSS (incidências/isenções) | C12: ____________________ | D12: ____________________
B13: IRRF (incidências/isenções) | C13: ____________________ | D13: ____________________
B14: Outras ressalvas | C14: ____________________ | D14: ____________________
